pystrings/__init__.py
pystrings/pystrings.py
pystrings-0.0.34.dist-info/LICENSE
pystrings-0.0.34.dist-info/METADATA
pystrings-0.0.34.dist-info/WHEEL
pystrings-0.0.34.dist-info/top_level.txt
pystrings-0.0.34.dist-info/RECORD
