Metadata-Version: 2.1
Name: pystrings
Version: 0.0.34
Summary: A package For ease of working with strings
Home-page: UNKNOWN
Author: Mahdi Gadget
Author-email: mahdigadget20@gmail.com
License: UNKNOWN
Platform: UNKNOWN
Classifier: License :: OSI Approved :: GNU General Public License v3 (GPLv3)
Classifier: Programming Language :: Python
Classifier: Programming Language :: Python :: 3
Classifier: Programming Language :: Python :: 3.6
Requires-Python: >=3.6.0
